resta/__init__.py
resta/endpoint.py
resta/request.py
resta/service.py
resta/url.py
resta/utils.py
RESTa-0.1.dist-info/LICENSE
RESTa-0.1.dist-info/METADATA
RESTa-0.1.dist-info/WHEEL
RESTa-0.1.dist-info/top_level.txt
RESTa-0.1.dist-info/RECORD
