Metadata-Version: 2.1
Name: RESTa
Version: 0.1
Summary: REST API client framework
Home-page: https://github.com/surabujin/resta
Author: Dmitry Bogun
Author-email: nyaka@nyaka.org
License: UNKNOWN
Platform: UNKNOWN
Classifier: Programming Language :: Python :: 3
Classifier: License :: OSI Approved :: Apache Software License
Classifier: Operating System :: OS Independent
Requires-Dist: requests
